efficientvit/__init__.py
efficientvit/ae_model_zoo.py
efficientvit/cls_model_zoo.py
efficientvit/diffusion_model_zoo.py
efficientvit/sam_model_zoo.py
efficientvit/seg_model_zoo.py
efficientvit/aecore/__init__.py
efficientvit/aecore/evaluator.py
efficientvit/aecore/data_provider/__init__.py
efficientvit/aecore/data_provider/base.py
efficientvit/aecore/data_provider/imagenet.py
efficientvit/apps/__init__.py
efficientvit/apps/setup.py
efficientvit/apps/data_provider/__init__.py
efficientvit/apps/data_provider/base.py
efficientvit/apps/data_provider/sampler.py
efficientvit/apps/data_provider/augment/__init__.py
efficientvit/apps/data_provider/augment/bbox.py
efficientvit/apps/data_provider/augment/color_aug.py
efficientvit/apps/data_provider/random_resolution/__init__.py
efficientvit/apps/data_provider/random_resolution/_data_loader.py
efficientvit/apps/data_provider/random_resolution/_data_worker.py
efficientvit/apps/data_provider/random_resolution/controller.py
efficientvit/apps/metrics/__init__.py
efficientvit/apps/metrics/fid/__init__.py
efficientvit/apps/metrics/fid/fid.py
efficientvit/apps/metrics/fid/inception.py
efficientvit/apps/metrics/inception_score/__init__.py
efficientvit/apps/metrics/inception_score/inception_score.py
efficientvit/apps/metrics/psnr/__init__.py
efficientvit/apps/metrics/psnr/psnr.py
efficientvit/apps/trainer/__init__.py
efficientvit/apps/trainer/base.py
efficientvit/apps/trainer/run_config.py
efficientvit/apps/utils/__init__.py
efficientvit/apps/utils/dist.py
efficientvit/apps/utils/ema.py
efficientvit/apps/utils/export.py
efficientvit/apps/utils/image.py
efficientvit/apps/utils/init.py
efficientvit/apps/utils/lr.py
efficientvit/apps/utils/metric.py
efficientvit/apps/utils/misc.py
efficientvit/apps/utils/opt.py
efficientvit/clscore/__init__.py
efficientvit/clscore/data_provider/__init__.py
efficientvit/clscore/data_provider/imagenet.py
efficientvit/clscore/trainer/__init__.py
efficientvit/clscore/trainer/cls_run_config.py
visaionefficientvit-0.2.0.dist-info/licenses/LICENSE
visaionefficientvit-0.2.0.dist-info/METADATA
visaionefficientvit-0.2.0.dist-info/WHEEL
visaionefficientvit-0.2.0.dist-info/top_level.txt
visaionefficientvit-0.2.0.dist-info/RECORD
