Metadata-Version: 2.4
Name: visaionefficientvit
Version: 0.2.0
Summary: Add your description here
Requires-Python: >=3.10
License-File: LICENSE
Requires-Dist: diffusers>=0.35.2
Requires-Dist: einops>=0.8.1
Requires-Dist: matplotlib>=3.10.7
Requires-Dist: omegaconf>=2.3.0
Requires-Dist: onnx==1.19.1
Requires-Dist: onnxruntime>=1.23.2
Requires-Dist: onnxsim>=0.4.36
Requires-Dist: opencv-python>=4.11.0.86
Requires-Dist: pycocotools>=2.0.10
Requires-Dist: pyyaml>=6.0.3
Requires-Dist: scikit-image>=0.24.0
Requires-Dist: scipy>=1.15.3
Requires-Dist: timm==0.9.5
Requires-Dist: torch>=2.7.1
Requires-Dist: torch-fidelity>=0.3.0
Requires-Dist: torchdiffeq>=0.2.5
Requires-Dist: torchvision>=0.22.1
Requires-Dist: visaionsegmentanything>=1.0
Dynamic: license-file
